.coveragerc
MANIFEST.in
README.rst
requirements.txt
runtests.py
setup.py
csnews/__init__.py
csnews/admin.py
csnews/feeds.py
csnews/models.py
csnews/urls.py
csnews/views.py
csnews.egg-info/PKG-INFO
csnews.egg-info/SOURCES.txt
csnews.egg-info/dependency_links.txt
csnews.egg-info/not-zip-safe
csnews.egg-info/requires.txt
csnews.egg-info/top_level.txt
csnews/migrations/0001_initial.py
csnews/migrations/__init__.py
csnews/templates/base.html
csnews/templates/news/archive.html
csnews/templates/news/article.html
csnews/templates/news/article_by_mail.html
csnews/templates/news/articles.html
csnews/tests/__init__.py
csnews/tests/tests.py
csnews/utils/load_data.py
csnews/utils/load_images.py